{
    "archinstall-language": "English",
    "audio_config": {
        "audio": "No audio server"
    },
    "bootloader": "Systemd-boot",
    "custom_commands": [],
    "disk_config": {
        "btrfs_options": {
            "snapshot_config": null
        },
        "config_type": "manual_partitioning",
        "device_modifications": [
            {
                "device": "/dev/nvme0n1",
                "partitions": [
                    {
                        "btrfs": [],
                        "dev_path": null,
                        "flags": [
                            "boot",
                            "esp"
                        ],
                        "fs_type": "fat32",
                        "mount_options": [],
                        "mountpoint": "/boot",
                        "obj_id": "a8fb913d-d0e2-44a9-8d08-bd415ae94694",
                        "size": {
                            "sector_size": {
                                "unit": "B",
                                "value": 512
                            },
                            "unit": "MiB",
                            "value": 512
                        },
                        "start": {
                            "sector_size": {
                                "unit": "B",
                                "value": 512
                            },
                            "unit": "MiB",
                            "value": 1
                        },
                        "status": "create",
                        "type": "primary"
                    },
                    {
                        "btrfs": [
                            {
                                "mountpoint": "/",
                                "name": "@root"
                            },
                            {
                                "mountpoint": "/home",
                                "name": "@home"
                            },
                            {
                                "mountpoint": "/recovery",
                                "name": "@recovery"
                            }
                        ],
                        "dev_path": null,
                        "flags": [],
                        "fs_type": "btrfs",
                        "mount_options": [],
                        "mountpoint": null,
                        "obj_id": "bd4b6a17-cd8a-4d65-b2da-faa04a0cd2c4",
                        "size": {
                            "sector_size": {
                                "unit": "B",
                                "value": 512
                            },
                            "unit": "B",
                            "value": 1023670222848
                        },
                        "start": {
                            "sector_size": {
                                "unit": "B",
                                "value": 512
                            },
                            "unit": "B",
                            "value": 537919488
                        },
                        "status": "create",
                        "type": "primary"
                    }
                ],
                "wipe": true
            }
        ]
    },
    "hostname": "archlinux",
    "kernels": [
        "linux"
    ],
    "locale_config": {
        "kb_layout": "pl",
        "sys_enc": "UTF-8",
        "sys_lang": "en_US.UTF-8"
    },
    "network_config": {
        "type": "nm"
    },
    "ntp": true,
    "packages": [],
    "parallel_downloads": 0,
    "profile_config": {
        "gfx_driver": null,
        "greeter": null,
        "profile": {
            "custom_settings": {},
            "details": [],
            "main": "Minimal"
        }
    },
    "services": [],
    "swap": false,
    "timezone": "Poland",
    "version": null
}